django_graphql_geojson-0.1.4.dist-info/DESCRIPTION.rst
django_graphql_geojson-0.1.4.dist-info/METADATA
django_graphql_geojson-0.1.4.dist-info/RECORD
django_graphql_geojson-0.1.4.dist-info/WHEEL
django_graphql_geojson-0.1.4.dist-info/metadata.json
django_graphql_geojson-0.1.4.dist-info/top_level.txt
graphql_geojson/__init__.py
graphql_geojson/converter.py
graphql_geojson/fields.py
graphql_geojson/filters.py
graphql_geojson/resolver.py
graphql_geojson/types/__init__.py
graphql_geojson/types/distance.py
graphql_geojson/types/feature.py
graphql_geojson/types/geometry.py
